rtl/microstructure/bram_microstructure.v
`timescale 1ns/1ps

/*
 * Synchronous BRAM for Microstructure Pipeline (VWAP Ring Buffer)
 *
 * This module infers a synchronous read, synchronous write RAM.
 * Synthesis directive `(* ram_style = "block" *)` enforces block RAM inference.
 * Read-before-write or Write-first behavior is often synthesis-dependent.
 * The Phase 2.2 pipeline explicitly separates BRAM read and BRAM write
 * into distinct cycles to guarantee correctness regardless of read-first
 * or write-first synthesis behavior.
 *
 * Port width: 120 bits (72-bit sum_pv + 48-bit sum_v)
 * Depth: 32 entries (20 ticks rounded up to nearest power of 2)
 */

module bram_microstructure (
    input  wire         clk,
    input  wire         we,
    input  wire [4:0]   addr,
    input  wire [119:0] din,
    output reg  [119:0] dout
);

    // Enforce Block RAM inference
    (* ram_style = "block" *) reg [119:0] ram [0:31];

    // Initialize to zero for simulation and FPGA bitstream
    integer i;
    initial begin
        for (i = 0; i < 32; i = i + 1) begin
            ram[i] = 120'd0;
        end
    end

    always @(posedge clk) begin
        if (we) begin
            ram[addr] <= din;
        end
        // Synchronous read (1-cycle latency)
        dout <= ram[addr];
    end

endmodule

rtl/testbench/bram_microstructure_tb.v
`timescale 1ns/1ps

module bram_microstructure_tb;

    reg clk;
    reg we;
    reg [4:0] addr;
    reg [119:0] din;
    wire [119:0] dout;

    bram_microstructure u_bram (
        .clk(clk),
        .we(we),
        .addr(addr),
        .din(din),
        .dout(dout)
    );

    initial begin
        clk = 0;
        forever #5 clk = ~clk;
    end

    initial begin
        $dumpfile("bram_microstructure_tb.vcd");
        $dumpvars(0, bram_microstructure_tb);
        
        we = 0;
        addr = 0;
        din = 0;
        
        #20;
        
        // Write to address 5
        @(posedge clk);
        we <= 1;
        addr <= 5;
        din <= 120'hAAAA_BBBB_CCCC_DDDD_EEEE_FFFF_1234_5678;
        
        @(posedge clk);
        we <= 0;
        
        // Read from address 5
        @(posedge clk);
        addr <= 5;
        
        @(posedge clk);
        // Data should be valid here (1-cycle read latency)
        #1;
        if (dout !== 120'hAAAA_BBBB_CCCC_DDDD_EEEE_FFFF_1234_5678) begin
            $display("ERROR: BRAM Read Failed. Expected AAAA_BBBB_CCCC_DDDD_EEEE_FFFF_1234_5678, got %h", dout);
            $finish;
        end
        
        // Write to address 19
        @(posedge clk);
        we <= 1;
        addr <= 19;
        din <= 120'h1111_2222_3333_4444_5555_6666_7777_8888;
        
        @(posedge clk);
        we <= 0;
        addr <= 19; // Keep reading 19
        
        @(posedge clk);
        #1;
        if (dout !== 120'h1111_2222_3333_4444_5555_6666_7777_8888) begin
            $display("ERROR: BRAM Read Failed. Expected 1111_2222_3333_4444_5555_6666_7777_8888, got %h", dout);
            $finish;
        end
        
        $display("BRAM tests passed.");
        $finish;
    end

endmodule

bram_microstructure_tb.vcd
$date
	Mon Jun  1 16:02:03 2026
$end
$version
	Icarus Verilog
$end
$timescale
	1ps
$end
$scope module bram_microstructure_tb $end
$var wire 120 ! dout [119:0] $end
$var reg 5 " addr [4:0] $end
$var reg 1 # clk $end
$var reg 120 $ din [119:0] $end
$var reg 1 % we $end
$scope module u_bram $end
$var wire 5 & addr [4:0] $end
$var wire 1 # clk $end
$var wire 120 ' din [119:0] $end
$var wire 1 % we $end
$var reg 120 ( dout [119:0] $end
$var integer 32 ) i [31:0] $end
$upscope $end
$upscope $end
$enddefinitions $end
$comment Show the parameter values. $end
$dumpall
$end
#0
$dumpvars
b100000 )
bx (
b0 '
b0 &
0%
b0 $
0#
b0 "
bx !
$end
#5000
b0 !
b0 (
1#
#10000
0#
#15000
1#
#20000
0#
#25000
b101010101011101110111011110011001100110011011101110111011110111011101110111111111111111100010010001101000101011001111000 $
b101010101011101110111011110011001100110011011101110111011110111011101110111111111111111100010010001101000101011001111000 '
b101 "
b101 &
1%
1#
#30000
0#
#35000
0%
1#
#40000
0#
#45000
b101010101011101110111011110011001100110011011101110111011110111011101110111111111111111100010010001101000101011001111000 !
b101010101011101110111011110011001100110011011101110111011110111011101110111111111111111100010010001101000101011001111000 (
1#
#50000
0#
#55000
1#
#60000
0#
#65000
b100010010001000100010001100110011001101000100010001000101010101010101011001100110011001110111011101111000100010001000 $
b100010010001000100010001100110011001101000100010001000101010101010101011001100110011001110111011101111000100010001000 '
b10011 "
b10011 &
1%
1#
#70000
0#
#75000
0%
b0 !
b0 (
1#
#80000
0#
#85000
b100010010001000100010001100110011001101000100010001000101010101010101011001100110011001110111011101111000100010001000 !
b100010010001000100010001100110011001101000100010001000101010101010101011001100110011001110111011101111000100010001000 (
1#
