rtl/microstructure/restoring_divider.v
`timescale 1ns/1ps

/*
 * Restoring Binary Divider
 *
 * Dividend: 72 bits (sum_pv)
 * Divisor:  48 bits (sum_v)
 * Quotient: 34 bits (vwap Q18.15)
 * Latency:  34 iteration cycles + 1 setup + 1 done = 36 cycles total
 *
 * State Transition Diagram:
 * IDLE -> (start & divisor == 0) -> ZERO_GUARD
 * IDLE -> (start & divisor != 0) -> CALC
 * CALC -> (count == 34) -> DONE
 * ZERO_GUARD -> DONE
 * DONE -> IDLE
 */

module restoring_divider (
    input  wire         clk,
    input  wire         rst_n,
    
    input  wire         start,
    input  wire [71:0]  dividend,
    input  wire [47:0]  divisor,
    
    output reg          done,
    output reg  [33:0]  quotient
);

    localparam STATE_IDLE       = 2'd0;
    localparam STATE_CALC       = 2'd1;
    localparam STATE_DONE       = 2'd2;
    localparam STATE_ZERO_GUARD = 2'd3;

    reg [1:0]  state;
    reg [5:0]  count;
    
    // R holds the remainder (up to 49 bits to accommodate shifted D)
    reg [48:0] R;
    // A holds the bottom bits of dividend, shifted out to become quotient
    reg [33:0] A;
    
    // Divisor latch
    reg [48:0] D;

    always @(posedge clk or negedge rst_n) begin
        if (!rst_n) begin
            state    <= STATE_IDLE;
            count    <= 6'd0;
            R        <= 49'd0;
            A        <= 34'd0;
            D        <= 49'd0;
            done     <= 1'b0;
            quotient <= 34'd0;
        end else begin
            // Default: done is a 1-cycle pulse
            done <= 1'b0;
            
            case (state)
                STATE_IDLE: begin
                    if (start) begin
                        if (divisor == 48'd0) begin
                            state <= STATE_ZERO_GUARD;
                        end else begin
                            // Initialize algorithm
                            // R gets the top 38 bits of the 72-bit dividend
                            R <= {11'd0, dividend[71:34]};
                            // A gets the bottom 34 bits of the dividend
                            A <= dividend[33:0];
                            // Latch divisor
                            D <= {1'b0, divisor};
                            
                            count <= 6'd0;
                            state <= STATE_CALC;
                        end
                    end
                end
                
                STATE_CALC: begin
                    if (count < 6'd34) begin
                        // 1. Shift (R, A) left by 1
                        // wire [48:0] next_R = {R[47:0], A[33]};
                        // wire [33:0] next_A = {A[32:0], 1'b0};
                        // 2. If next_R >= D, next_R -= D and next_A[0] = 1
                        
                        if ({R[47:0], A[33]} >= D) begin
                            R <= {R[47:0], A[33]} - D;
                            A <= {A[32:0], 1'b1};
                        end else begin
                            R <= {R[47:0], A[33]};
                            A <= {A[32:0], 1'b0};
                        end
                        
                        count <= count + 1'b1;
                    end else begin
                        state <= STATE_DONE;
                    end
                end
                
                STATE_ZERO_GUARD: begin
                    A <= 34'd0;
                    state <= STATE_DONE;
                end
                
                STATE_DONE: begin
                    quotient <= A;
                    done     <= 1'b1;
                    state    <= STATE_IDLE;
                end
                
                default: state <= STATE_IDLE;
            endcase
        end
    end

endmodule

rtl/testbench/restoring_divider_tb.v
`timescale 1ns/1ps

module restoring_divider_tb;

    reg clk;
    reg rst_n;
    
    reg start;
    reg [71:0] dividend;
    reg [47:0] divisor;
    
    wire done;
    wire [33:0] quotient;

    restoring_divider u_div (
        .clk(clk),
        .rst_n(rst_n),
        .start(start),
        .dividend(dividend),
        .divisor(divisor),
        .done(done),
        .quotient(quotient)
    );

    initial begin
        clk = 0;
        forever #5 clk = ~clk;
    end

    initial begin
        $dumpfile("restoring_divider_tb.vcd");
        $dumpvars(0, restoring_divider_tb);
        
        rst_n = 0;
        start = 0;
        dividend = 0;
        divisor = 0;
        
        #20;
        rst_n = 1;
        #20;
        
        // Test 1: Normal Division
        // 1000 / 5 = 200
        @(posedge clk);
        start <= 1;
        dividend <= 72'd1000;
        divisor <= 48'd5;
        
        @(posedge clk);
        start <= 0;
        
        wait(done);
        if (quotient !== 34'd200) begin
            $display("ERROR: 1000 / 5 failed. Got %d", quotient);
            $finish;
        end
        $display("Test 1 Passed: 1000 / 5 = 200");
        
        #20;
        
        // Test 2: sum_v = 0 (Zero Guard)
        @(posedge clk);
        start <= 1;
        dividend <= 72'd50000;
        divisor <= 48'd0;
        
        @(posedge clk);
        start <= 0;
        
        wait(done);
        if (quotient !== 34'd0) begin
            $display("ERROR: Zero guard failed. Got %d", quotient);
            $finish;
        end
        $display("Test 2 Passed: 50000 / 0 = 0 (Guard)");
        
        #20;
        
        // Test 3: Minimum non-zero divisor (1)
        @(posedge clk);
        start <= 1;
        dividend <= 72'd987654321;
        divisor <= 48'd1;
        
        @(posedge clk);
        start <= 0;
        
        wait(done);
        if (quotient !== 34'd987654321) begin
            $display("ERROR: Divisor=1 failed. Got %d", quotient);
            $finish;
        end
        $display("Test 3 Passed: 987654321 / 1 = 987654321");
        
        #20;
        
        // Test 4: Maximum Quotient (2^34 - 1)
        @(posedge clk);
        start <= 1;
        dividend <= {38'd0, 34'h3FFFFFFFF}; // (1<<34)-1
        divisor <= 48'd1;
        
        @(posedge clk);
        start <= 0;
        
        wait(done);
        if (quotient !== 34'h3FFFFFFFF) begin
            $display("ERROR: Max quotient failed. Got %h", quotient);
            $finish;
        end
        $display("Test 4 Passed: (2^34 - 1) / 1 = 2^34 - 1");
        
        $display("All restoring_divider tests passed.");
        $finish;
    end

endmodule

restoring_divider_tb.vcd
$date
	Mon Jun  1 16:03:27 2026
$end
$version
	Icarus Verilog
$end
$timescale
	1ps
$end
$scope module restoring_divider_tb $end
$var wire 34 ! quotient [33:0] $end
$var wire 1 " done $end
$var reg 1 # clk $end
$var reg 72 $ dividend [71:0] $end
$var reg 48 % divisor [47:0] $end
$var reg 1 & rst_n $end
$var reg 1 ' start $end
$scope module u_div $end
$var wire 1 # clk $end
$var wire 72 ( dividend [71:0] $end
$var wire 48 ) divisor [47:0] $end
$var wire 1 & rst_n $end
$var wire 1 ' start $end
$var parameter 2 * STATE_CALC $end
$var parameter 2 + STATE_DONE $end
$var parameter 2 , STATE_IDLE $end
$var parameter 2 - STATE_ZERO_GUARD $end
$var reg 34 . A [33:0] $end
$var reg 49 / D [48:0] $end
$var reg 49 0 R [48:0] $end
$var reg 6 1 count [5:0] $end
$var reg 1 " done $end
$var reg 34 2 quotient [33:0] $end
$var reg 2 3 state [1:0] $end
$upscope $end
$upscope $end
$enddefinitions $end
$comment Show the parameter values. $end
$dumpall
b11 -
b0 ,
b10 +
b1 *
$end
#0
$dumpvars
b0 3
b0 2
b0 1
b0 0
b0 /
b0 .
b0 )
b0 (
0'
0&
b0 %
b0 $
0#
0"
b0 !
$end
#5000
1#
#10000
0#
#15000
1#
#20000
0#
1&
#25000
1#
#30000
0#
#35000
1#
#40000
0#
#45000
b101 %
b101 )
b1111101000 $
b1111101000 (
1'
1#
#50000
0#
#55000
b1 3
b101 /
b1111101000 .
0'
1#
#60000
0#
#65000
b1 1
b11111010000 .
1#
#70000
0#
#75000
b10 1
b111110100000 .
1#
#80000
0#
#85000
b11 1
b1111101000000 .
1#
#90000
0#
#95000
b100 1
b11111010000000 .
1#
#100000
0#
#105000
b101 1
b111110100000000 .
1#
#110000
0#
#115000
b110 1
b1111101000000000 .
1#
#120000
0#
#125000
b111 1
b11111010000000000 .
1#
#130000
0#
#135000
b1000 1
b111110100000000000 .
1#
#140000
0#
#145000
b1001 1
b1111101000000000000 .
1#
#150000
0#
#155000
b1010 1
b11111010000000000000 .
1#
#160000
0#
#165000
b1011 1
b111110100000000000000 .
1#
#170000
0#
#175000
b1100 1
b1111101000000000000000 .
1#
#180000
0#
#185000
b1101 1
b11111010000000000000000 .
1#
#190000
0#
#195000
b1110 1
b111110100000000000000000 .
1#
#200000
0#
#205000
b1111 1
b1111101000000000000000000 .
1#
#210000
0#
#215000
b10000 1
b11111010000000000000000000 .
1#
#220000
0#
#225000
b10001 1
b111110100000000000000000000 .
1#
#230000
0#
#235000
b10010 1
b1111101000000000000000000000 .
1#
#240000
0#
#245000
b10011 1
b11111010000000000000000000000 .
1#
#250000
0#
#255000
b10100 1
b111110100000000000000000000000 .
1#
#260000
0#
#265000
b10101 1
b1111101000000000000000000000000 .
1#
#270000
0#
#275000
b10110 1
b11111010000000000000000000000000 .
1#
#280000
0#
#285000
b10111 1
b111110100000000000000000000000000 .
1#
#290000
0#
#295000
b11000 1
b1111101000000000000000000000000000 .
1#
#300000
0#
#305000
b11001 1
b1111010000000000000000000000000000 .
b1 0
1#
#310000
0#
#315000
b11010 1
b1110100000000000000000000000000000 .
b11 0
1#
#320000
0#
#325000
b11011 1
b1101000000000000000000000000000001 .
b10 0
1#
#330000
0#
#335000
b11100 1
b1010000000000000000000000000000011 .
b0 0
1#
#340000
0#
#345000
b11101 1
b100000000000000000000000000000110 .
b1 0
1#
#350000
0#
#355000
b11110 1
b1000000000000000000000000000001100 .
b10 0
1#
#360000
0#
#365000
b11111 1
b11001 .
b0 0
1#
#370000
0#
#375000
b100000 1
b110010 .
1#
#380000
0#
#385000
b100001 1
b1100100 .
1#
#390000
0#
#395000
b100010 1
b11001000 .
1#
#400000
0#
#405000
b10 3
1#
#410000
0#
#415000
b0 3
1"
b11001000 !
b11001000 2
1#
#420000
0#
#425000
0"
1#
#430000
0#
#435000
b0 %
b0 )
b1100001101010000 $
b1100001101010000 (
1'
1#
#440000
0#
#445000
b11 3
0'
1#
#450000
0#
#455000
b10 3
b0 .
1#
#460000
0#
#465000
b0 3
1"
b0 !
b0 2
1#
#470000
0#
#475000
0"
1#
#480000
0#
#485000
b1 %
b1 )
b111010110111100110100010110001 $
b111010110111100110100010110001 (
1'
1#
#490000
0#
#495000
b1 3
b0 1
b1 /
b111010110111100110100010110001 .
0'
1#
#500000
0#
#505000
b1 1
b1110101101111001101000101100010 .
1#
#510000
0#
#515000
b10 1
b11101011011110011010001011000100 .
1#
#520000
0#
#525000
b11 1
b111010110111100110100010110001000 .
1#
#530000
0#
#535000
b100 1
b1110101101111001101000101100010000 .
1#
#540000
0#
#545000
b101 1
b1101011011110011010001011000100001 .
1#
#550000
0#
#555000
b110 1
b1010110111100110100010110001000011 .
1#
#560000
0#
#565000
b111 1
b101101111001101000101100010000111 .
1#
#570000
0#
#575000
b1000 1
b1011011110011010001011000100001110 .
1#
#580000
0#
#585000
b1001 1
b110111100110100010110001000011101 .
1#
#590000
0#
#595000
b1010 1
b1101111001101000101100010000111010 .
1#
#600000
0#
#605000
b1011 1
b1011110011010001011000100001110101 .
1#
#610000
0#
#615000
b1100 1
b111100110100010110001000011101011 .
1#
#620000
0#
#625000
b1101 1
b1111001101000101100010000111010110 .
1#
#630000
0#
#635000
b1110 1
b1110011010001011000100001110101101 .
1#
#640000
0#
#645000
b1111 1
b1100110100010110001000011101011011 .
1#
#650000
0#
#655000
b10000 1
b1001101000101100010000111010110111 .
1#
#660000
0#
#665000
b10001 1
b11010001011000100001110101101111 .
1#
#670000
0#
#675000
b10010 1
b110100010110001000011101011011110 .
1#
#680000
0#
#685000
b10011 1
b1101000101100010000111010110111100 .
1#
#690000
0#
#695000
b10100 1
b1010001011000100001110101101111001 .
1#
#700000
0#
#705000
b10101 1
b100010110001000011101011011110011 .
1#
#710000
0#
#715000
b10110 1
b1000101100010000111010110111100110 .
1#
#720000
0#
#725000
b10111 1
b1011000100001110101101111001101 .
1#
#730000
0#
#735000
b11000 1
b10110001000011101011011110011010 .
1#
#740000
0#
#745000
b11001 1
b101100010000111010110111100110100 .
1#
#750000
0#
#755000
b11010 1
b1011000100001110101101111001101000 .
1#
#760000
0#
#765000
b11011 1
b110001000011101011011110011010001 .
1#
#770000
0#
#775000
b11100 1
b1100010000111010110111100110100010 .
1#
#780000
0#
#785000
b11101 1
b1000100001110101101111001101000101 .
1#
#790000
0#
#795000
b11110 1
b1000011101011011110011010001011 .
1#
#800000
0#
#805000
b11111 1
b10000111010110111100110100010110 .
1#
#810000
0#
#815000
b100000 1
b100001110101101111001101000101100 .
1#
#820000
0#
#825000
b100001 1
b1000011101011011110011010001011000 .
1#
#830000
0#
#835000
b100010 1
b111010110111100110100010110001 .
1#
#840000
0#
#845000
b10 3
1#
#850000
0#
#855000
b0 3
1"
b111010110111100110100010110001 !
b111010110111100110100010110001 2
1#
#860000
0#
#865000
0"
1#
#870000
0#
#875000
b1111111111111111111111111111111111 $
b1111111111111111111111111111111111 (
1'
1#
#880000
0#
#885000
b1 3
b0 1
b1111111111111111111111111111111111 .
0'
1#
#890000
0#
#895000
b1 1
1#
#900000
0#
#905000
b10 1
1#
#910000
0#
#915000
b11 1
1#
#920000
0#
#925000
b100 1
1#
#930000
0#
#935000
b101 1
1#
#940000
0#
#945000
b110 1
1#
#950000
0#
#955000
b111 1
1#
#960000
0#
#965000
b1000 1
1#
#970000
0#
#975000
b1001 1
1#
#980000
0#
#985000
b1010 1
1#
#990000
0#
#995000
b1011 1
1#
#1000000
0#
#1005000
b1100 1
1#
#1010000
0#
#1015000
b1101 1
1#
#1020000
0#
#1025000
b1110 1
1#
#1030000
0#
#1035000
b1111 1
1#
#1040000
0#
#1045000
b10000 1
1#
#1050000
0#
#1055000
b10001 1
1#
#1060000
0#
#1065000
b10010 1
1#
#1070000
0#
#1075000
b10011 1
1#
#1080000
0#
#1085000
b10100 1
1#
#1090000
0#
#1095000
b10101 1
1#
#1100000
0#
#1105000
b10110 1
1#
#1110000
0#
#1115000
b10111 1
1#
#1120000
0#
#1125000
b11000 1
1#
#1130000
0#
#1135000
b11001 1
1#
#1140000
0#
#1145000
b11010 1
1#
#1150000
0#
#1155000
b11011 1
1#
#1160000
0#
#1165000
b11100 1
1#
#1170000
0#
#1175000
b11101 1
1#
#1180000
0#
#1185000
b11110 1
1#
#1190000
0#
#1195000
b11111 1
1#
#1200000
0#
#1205000
b100000 1
1#
#1210000
0#
#1215000
b100001 1
1#
#1220000
0#
#1225000
b100010 1
1#
#1230000
0#
#1235000
b10 3
1#
#1240000
0#
#1245000
b0 3
1"
b1111111111111111111111111111111111 !
b1111111111111111111111111111111111 2
1#
